fast_kafka_api/__init__.py
fast_kafka_api/_cli.py
fast_kafka_api/_example.py
fast_kafka_api/_modidx.py
fast_kafka_api/application.py
fast_kafka_api/asyncapi.py
fast_kafka_api/logger.py
fast_kafka_api/testing.py
fast_kafka_api/_components/__init__.py
fast_kafka_api/_components/aiokafka_consumer_loop.py
fast_kafka_api/_components/aiokafka_loop.py
fast_kafka_api/_components/aiokafka_producer_loop.py
fast_kafka_api/_components/aiokafka_producer_manager.py
fast_kafka_api/_components/asyncapi.py
fast_kafka_api/_components/logger.py
fast_kafka_api-0.0.4.dist-info/LICENSE
fast_kafka_api-0.0.4.dist-info/METADATA
fast_kafka_api-0.0.4.dist-info/WHEEL
fast_kafka_api-0.0.4.dist-info/entry_points.txt
fast_kafka_api-0.0.4.dist-info/top_level.txt
fast_kafka_api-0.0.4.dist-info/RECORD
