Metadata-Version: 2.1
Name: fast-kafka-api
Version: 0.0.4
Summary: Extension of FastAPI with Kafka event handlers
Home-page: https://github.com/airtai/fast-kafka-api
Author: airt
Author-email: info@airt.ai
License: Apache Software License 2.0
Keywords: nbdev jupyter notebook python
Platform: UNKNOWN
Classifier: Development Status :: 4 - Beta
Classifier: Intended Audience :: Developers
Classifier: Natural Language :: English
Classifier: Programming Language :: Python :: 3.8
Classifier: Programming Language :: Python :: 3.9
Classifier: Programming Language :: Python :: 3.10
Classifier: License :: OSI Approved :: Apache Software License
Requires-Python: >=3.8
License-File: LICENSE
Requires-Dist: aiofiles (>=22.1.0)
Requires-Dist: aiokafka (>=0.8.0)
Requires-Dist: asyncer (>=0.0.2)
Requires-Dist: confluent-kafka (>=1.9.2)
Requires-Dist: fastapi (>=0.85.1)
Requires-Dist: httpx (>=0.23.0)
Requires-Dist: python-multipart (>=0.0.5)
Requires-Dist: requests (>=2.28.1)
Provides-Extra: dev
Requires-Dist: bandit (>=1.7.4) ; extra == 'dev'
Requires-Dist: black (>=22.10.0) ; extra == 'dev'
Requires-Dist: email-validator (>=1.3.0) ; extra == 'dev'
Requires-Dist: isort (>=5.11.4) ; extra == 'dev'
Requires-Dist: mypy (>=0.991) ; extra == 'dev'
Requires-Dist: nbconvert ; extra == 'dev'
Requires-Dist: nbdev-mkdocs (>=0.0.3) ; extra == 'dev'
Requires-Dist: nbqa (>=1.6.0) ; extra == 'dev'
Requires-Dist: nest-asyncio (>=1.5.6) ; extra == 'dev'
Requires-Dist: numpy (>=1.21.0) ; extra == 'dev'
Requires-Dist: pandas (>=1.2.0) ; extra == 'dev'
Requires-Dist: pre-commit (>=2.21.0) ; extra == 'dev'
Requires-Dist: pytest (>=7.1.0) ; extra == 'dev'
Requires-Dist: semgrep (>=1.3.0) ; extra == 'dev'
Requires-Dist: uvicorn (>=0.20) ; extra == 'dev'
